platonic_queue/__init__.py
platonic_queue/chunkify.py
platonic_queue/list.py
platonic_queue/py.typed
platonic_queue/queue.py
platonic_queue/serde.py
platonic_queue/sqs.py
platonic_queue-0.2.0.dist-info/LICENSE
platonic_queue-0.2.0.dist-info/WHEEL
platonic_queue-0.2.0.dist-info/METADATA
platonic_queue-0.2.0.dist-info/RECORD
