Metadata-Version: 2.1
Name: platonic-queue
Version: 0.2.0
Summary: Abstract acknowledgement queue concept, implemented over multiple backends.
Home-page: https://github.com/platonic/platonic-queue
License: MIT
Requires-Python: >=3.6,<4.0
Classifier: Development Status :: 3 - Alpha
Classifier: Intended Audience :: Developers
Classifier: License :: OSI Approved :: MIT License
Classifier: Operating System :: OS Independent
Classifier: Programming Language :: Python :: 3
Classifier: Programming Language :: Python :: 3.6
Classifier: Programming Language :: Python :: 3.7
Classifier: Programming Language :: Python :: 3.8
Classifier: Topic :: Software Development :: Libraries :: Python Modules
Requires-Dist: boto3[sqs] (>=1.14.8,<2.0.0)
Requires-Dist: boto3_type_annotations[sqs] (>=0.3.1,<0.4.0)
Project-URL: Repository, https://github.com/platonic/platonic-queue
